diffable_sql/__init__.py
diffable_sql/__main__.py
diffable_sql/cli.py
diffable_sql-0.2.0.dist-info/METADATA
diffable_sql-0.2.0.dist-info/WHEEL
diffable_sql-0.2.0.dist-info/entry_points.txt
diffable_sql-0.2.0.dist-info/RECORD
