Metadata-Version: 2.1
Name: diffable-sql
Version: 0.2.0
Summary: Output normalised diffable database schemas
Author: Tom Forbes
Author-email: tom@tomforb.es
Requires-Python: >=3.10,<4.0
Classifier: Programming Language :: Python :: 3
Classifier: Programming Language :: Python :: 3.10
Classifier: Programming Language :: Python :: 3.11
Provides-Extra: postgres
Requires-Dist: SQLAlchemy (>=2.0.15,<3.0.0)
Requires-Dist: click (>=8.1.3,<9.0.0)
Requires-Dist: psycopg2-binary (>=2.9,<3.0) ; extra == "postgres"
